[
  {
    "description": "全国の公共体育館や関連施設における詳細利用料金・予約システム・具体例ガイド（極限深掘り版）",
    "updated_at": "2026-03-03T12:00:00Z",
    "general_instructions": {
      "title": "公共体育館を利用する際の共通ルールと裏技",
      "guidelines": [
        "【団体予約の壁】利用には事前の「団体登録」または「個人登録」が必要な自治体がほとんどです。多くの自治体では「市内（区内）在住・在勤・在学者が半数以上の5名〜10名以上の団体」のみ登録可能という高いハードルがあります。",
        "【抽選と空き枠】団体利用の場合は、抽選予約（利用月の1〜2ヶ月前）に参加するのが一般的です。抽選後の空き枠は先着順（ネット予約）になります。",
        "【個人開放・オープンプレイ】個人利用枠（一般公開日）の場合は、当日窓口で直接券を購入（300円〜500円程度）して利用可能です。港区スポーツセンターや日環アリーナ栃木などで定期開催されています。",
        "【必須アイテム】インドアシューズ（体育館履き）は必須です。公共施設ではバドミントン支柱を下げてネットを代用することがほとんどで、ピックルボール専用ポータブルネットの完備はごく一部です。"
      ]
    },
    "regional_price_estimates": [
      {
        "region": "東京・関東エリア",
        "reservation_system_examples": [
          "東京都スポーツ施設サービス",
          "港区施設予約システム",
          "横浜市市民利用施設予約システム"
        ],
        "group_rental": {
          "description": "団体貸切（1面・2時間あたり）",
          "price_range": "1,000円 〜 4,000円",
          "concrete_examples": [
            "東京体育館（サブアリーナ）: 団体貸切のみ。専用利用は料金が高額だが設備は最高峰。",
            "横浜市スポーツセンター: 約3,000円/2h（バドミントンコート相当面積）。"
          ]
        },
        "individual_use": {
          "description": "個人開放利用（1回あたり）",
          "price_range": "300円 〜 800円",
          "concrete_examples": [
            "港区スポーツセンター: 区民・在勤者は500円、区外一般は800円。混雑時は抽選。",
            "日環アリーナ栃木: 個人参加型プログラムとして1回700円（パドルレンタル有）。"
          ]
        },
        "notes": "東京都心部は「区民であること」の縛りが強いですが、「個人開放（オープンプレイ）」であれば区外からのビジター参加も数百円の割増で可能な施設が多いです。"
      },
      {
        "region": "近畿・関西エリア",
        "reservation_system_examples": [
          "大阪市オーパス・スポーツ施設情報システム（OPASシステム）",
          "オーパス（OPAS）連携各市"
        ],
        "group_rental": {
          "description": "団体貸切（1面・1時間〜2時間あたり）",
          "price_range": "1,200円 〜 5,000円（照明代含む）",
          "concrete_examples": [
            "南港中央庭球場（大阪市）: コート利用料 1面1時間 900円 ＋ ナイター照明代 2,700円/時間 = 夜間は実質3,600円/時間。OPASシステムでの事前抽選（2ヶ月前）。"
          ]
        },
        "individual_use": {
          "description": "個人開放利用（1回あたり）",
          "price_range": "400円 〜 800円",
          "concrete_examples": [
            "大阪市立スポーツセンター各館: バドミントン開放日に準じて参加可能。利用料数百円。"
          ]
        },
        "notes": "関西（特に大阪）は「OPAS（オーパス）システム」への事前登録が必須となるケースが多いです。屋外コートのナイター利用は照明代（2000円〜3000円/h）がコート代よりも高くつく点に注意が必要です。"
      },
      {
        "region": "中部・東海エリア",
        "reservation_system_examples": [
          "名古屋市スポーツ・レクリエーション情報システム"
        ],
        "group_rental": {
          "description": "団体貸切（1面・2時間あたり）",
          "price_range": "800円 〜 2,500円",
          "concrete_examples": [
            "愛知県内の市民体育館: 1,500円〜2,000円/2h 程度。駐車場無料。"
          ]
        },
        "individual_use": {
          "description": "個人開放利用（1回あたり）",
          "price_range": "200円 〜 400円",
          "concrete_examples": [
            "岐阜メモリアルセンター / OKBアリーナ: リーズナブルな料金で利用可能。"
          ]
        },
        "notes": "中部エリアは関東・関西に比べて利用料金が安価で、かつ巨大な無料駐車場が完備されている施設が多いのが最大の特徴です。車での遠征に非常に向いています。"
      },
      {
        "region": "北海道・東北、中国・四国、九州・沖縄エリア（地方都市）",
        "reservation_system_examples": [
          "各市町村の独自予約システム または 直接電話・窓口受付"
        ],
        "group_rental": {
          "description": "団体貸切（1面・2時間あたり）",
          "price_range": "500円 〜 1,500円",
          "concrete_examples": [
            "青森市総合体育館: アリーナ利用料等、数百円〜千円台と格安。",
            "九州地方のB&G海洋センター: 1時間数百円の激安料金設定が多い。"
          ]
        },
        "individual_use": {
          "description": "個人開放利用（1回あたり）",
          "price_range": "100円 〜 300円",
          "concrete_examples": [
            "地方の市民体育館: 一般100円〜200円の入場券で時間無制限の場所もある。"
          ]
        },
        "notes": "地方都市の公共体育館は利用料が破格に安く設定されていますが、オンライン予約システムが未整備で「窓口での来館予約のみ」「電話予約のみ」というアナログな施設がいまだに多い点に注意です。また、暖房費（冬期間）が別途加算されるケース（北海道・東北）があります。"
      }
    ],
    "faq": [
      {
        "question": "「個人利用」でピックルボールの練習はできますか？",
        "answer": "バドミントンの個人利用（一般公開）枠がある体育館であれば可能な場合が多いですが、施設によっては「バドミントン専用（軟式テニスやピックルボールは不可）」として厳しいルールを定めている場合があるため、必ず事前の電話確認（「ピックルボールは打てますか？」）を推奨します。"
      },
      {
        "question": "ネットの貸し出しはありますか？",
        "answer": "バドミントンコートを使用する場合はバドミントンネットを中央まで下げて代用するのが最も一般的です（たるみますがプレーは可能です）。ピックルボール専用のポータブルネットを無料で貸し出している公共施設はごくわずか（日環アリーナ栃木など一部）です。本格的なプレーには自前のポータブルネット（2万円〜3万円程度）の持ち込みが必須です。"
      }
    ]
  },
  {
    "description": "ピックルボール専門施設（専用コート）の料金相場ガイド",
    "updated_at": "2026-03-03T12:00:00Z",
    "facility_type": "専門施設（専用コート）",
    "overview": "ピックルボール専用に設計されたインドア施設の料金ガイド。VIPインドア東陽町やKPI PARKのような専用施設は、コート品質・設備が充実している反面、利用料金は公共施設より高め。",
    "price_ranges": {
      "court_rental_per_hour": "2,000円 〜 5,000円（1面あたり）",
      "lesson_single": "3,000円 〜 5,000円（1回60〜90分）",
      "open_play": "1,500円 〜 3,000円（1回2時間程度）",
      "monthly_membership": "8,000円 〜 15,000円"
    },
    "notes": "専門施設は冷暖房完備・専用ネット常設・パドルレンタル完備など初心者に最も優しい環境。体験会は無料〜1,500円程度で実施される場合が多い。"
  },
  {
    "description": "テニスコート転用施設の料金相場ガイド",
    "updated_at": "2026-03-03T12:00:00Z",
    "facility_type": "テニスコート転用",
    "overview": "テニスコートにピックルボールのラインを追加して利用する施設の料金ガイド。テニスコート1面からピックルボール2〜4面を設営可能。",
    "price_ranges": {
      "court_rental_per_hour": "800円 〜 2,000円（テニスコート1面分）",
      "private_lesson": "要問い合わせ"
    },
    "notes": "テニスクラブがピックルボールの時間帯を設けているケースが増加。モリオカロイヤルテニスクラブなどが代表例。アウトドアのハードコートで使用でき、開放感がある。"
  },
  {
    "description": "民間スポーツクラブ（セントラル等）のピックルボール料金ガイド",
    "updated_at": "2026-03-03T12:00:00Z",
    "facility_type": "民間スポーツクラブ",
    "overview": "セントラルスポーツやコナミスポーツなどの大手フィットネスクラブが提供するピックルボールプログラムの料金ガイド。",
    "price_ranges": {
      "member_additional_fee": "0円 〜 1,000円（会員は追加料金なしの場合あり）",
      "non_member_single_visit": "1,500円 〜 3,000円",
      "monthly_membership": "6,000円 〜 12,000円（フルメンバーシップの一部として）"
    },
    "notes": "クラブ会員であれば追加費用なしでピックルボールプログラムに参加できるケースが多い。パドルやボールの貸し出しも完備されていることが多く、手ぶらで参加可能。"
  },
  {
    "description": "ラウンドワン スポッチャのピックルボール料金ガイド",
    "updated_at": "2026-03-03T12:00:00Z",
    "facility_type": "ラウンドワン スポッチャ",
    "overview": "全国のラウンドワン スポッチャ内で手軽にピックルボールが楽しめる。他のスポーツやアクティビティも同時に楽しめるのが魅力。",
    "price_ranges": {
      "weekday_3hours": "2,000円 〜 3,000円（スポッチャ入場料に含む）",
      "weekend_3hours": "2,500円 〜 3,500円（スポッチャ入場料に含む）",
      "student_discount": "学生割引あり"
    },
    "notes": "ピックルボール専用の料金は不要で、スポッチャの入場料に含まれる。手ぶらでOK。ただしコートサイズや設備は本格的な施設には及ばないため、体験・入門向け。"
  }
]